{
  "rooms": [
    {
      "room": "balcony",
      "position": "east",
      "dimensions": {},
      "adjacent_rooms": [
        "common room",
        "master room"
      ],
      "directions": [
        "east",
        "south"
      ]
    },
    {
      "room": "balcony",
      "position": "north",
      "dimensions": {},
      "adjacent_rooms": [],
      "directions": [
        "north",
        "west"
      ]
    },
    {
      "room": "living room",
      "position": null,
      "dimensions": {},
      "adjacent_rooms": [],
      "directions": []
    },
    {
      "room": "balcony",
      "position": "east",
      "dimensions": {},
      "adjacent_rooms": [
        "living room"
      ],
      "directions": [
        "east"
      ]
    },
    {
      "room": "common room",
      "position": "west",
      "dimensions": {},
      "adjacent_rooms": [
        "kitchen"
      ],
      "directions": [
        "west"
      ]
    },
    {
      "room": "master room",
      "position": null,
      "dimensions": {},
      "adjacent_rooms": [
        "living room"
      ],
      "directions": []
    },
    {
      "room": "kitchen",
      "position": "north",
      "dimensions": {},
      "adjacent_rooms": [],
      "directions": [
        "north",
        "east"
      ]
    },
    {
      "room": "master room",
      "position": "south",
      "dimensions": {},
      "adjacent_rooms": [],
      "directions": [
        "south",
        "south",
        "north"
      ]
    },
    {
      "room": "balcony",
      "position": null,
      "dimensions": {},
      "adjacent_rooms": [
        "kitchen"
      ],
      "directions": []
    }
  ],
  "total_rooms": 9,
  "raw_text": "The balcony is in the east south corner and it is next to the common room and  master room. The size of the balcony is about 8*10 The bath room is in the north west corner. It is next to the living room. the size of the bath room is 8 feet width and 8 feet length. The coon room facing to the east direction and it is located in between the balcony and the living room. the size of the common room is15*15 Kitchen is in the west direction . It is located between the master room and the living room . the size is about 10*8 The ling room is in the north east corner and it is next to the common, master, kitchen and common bath. It is in the size of 15 width and 20 length The master room facing south direction and located in the south north corner. it is between the balcony and kitchen. the size is about 15*20",
  "total_square_footage": 0,
  "id": "2701",
  "source_annotation": "data/raw/annotations/2701.txt",
  "source_image": "data/raw/images/2701.png"
}