{
  "rooms": [
    {
      "room": "balcony",
      "position": "east",
      "dimensions": {},
      "adjacent_rooms": [
        "living room"
      ],
      "directions": [
        "east"
      ]
    },
    {
      "room": "bathroom",
      "position": "west",
      "dimensions": {},
      "adjacent_rooms": [
        "living room",
        "master room",
        "common room"
      ],
      "directions": [
        "west"
      ]
    },
    {
      "room": "common room",
      "position": "south",
      "dimensions": {},
      "adjacent_rooms": [
        "living room",
        "bathroom"
      ],
      "directions": [
        "south",
        "west"
      ]
    },
    {
      "room": "kitchen",
      "position": "south",
      "dimensions": {},
      "adjacent_rooms": [
        "living room"
      ],
      "directions": [
        "south",
        "east"
      ]
    },
    {
      "room": "living room",
      "position": "east",
      "dimensions": {},
      "adjacent_rooms": [],
      "directions": [
        "east"
      ]
    },
    {
      "room": "master room",
      "position": "north",
      "dimensions": {},
      "adjacent_rooms": [
        "living room",
        "bathroom"
      ],
      "directions": [
        "north",
        "west"
      ]
    }
  ],
  "total_rooms": 6,
  "raw_text": "balcony is in east side of the house, next to living room, size is 60 sq ft. bathroom is in west side of the house, next to living room, master room and common room, size is 36 sq ft. common room is in south west corner of the house, next to living room and bathroom, size is 120 sq ft. kitchen is in south east corner of the house, next to living room, size is 48 sq ft. living room is in east side of the house, next to all spaces, size is 470 sq ft. master room is in north west corner of the house, next to living room and bathroom, size is 140 sq ft.",
  "total_square_footage": 0,
  "id": "31174",
  "source_annotation": "data/raw/annotations/31174.txt",
  "source_image": "data/raw/images/31174.png"
}