{
  "rooms": [
    {
      "room": "balcony",
      "position": null,
      "dimensions": {},
      "adjacent_rooms": [
        "living room"
      ],
      "directions": []
    },
    {
      "room": "bathroom",
      "position": null,
      "dimensions": {},
      "adjacent_rooms": [
        "living room"
      ],
      "directions": []
    },
    {
      "room": "bathroom",
      "position": null,
      "dimensions": {},
      "adjacent_rooms": [
        "living room"
      ],
      "directions": []
    },
    {
      "room": "common room",
      "position": null,
      "dimensions": {},
      "adjacent_rooms": [
        "living room"
      ],
      "directions": []
    },
    {
      "room": "living room",
      "position": null,
      "dimensions": {},
      "adjacent_rooms": [],
      "directions": []
    },
    {
      "room": "common room",
      "position": "northeast",
      "dimensions": {},
      "adjacent_rooms": [],
      "directions": [
        "northeast"
      ]
    },
    {
      "room": "kitchen",
      "position": null,
      "dimensions": {},
      "adjacent_rooms": [
        "living room"
      ],
      "directions": []
    },
    {
      "room": "kitchen",
      "position": "northeast",
      "dimensions": {},
      "adjacent_rooms": [],
      "directions": [
        "northeast"
      ]
    },
    {
      "room": "living room",
      "position": "west",
      "dimensions": {},
      "adjacent_rooms": [],
      "directions": [
        "west"
      ]
    },
    {
      "room": "master room",
      "position": null,
      "dimensions": {},
      "adjacent_rooms": [
        "living room"
      ],
      "directions": []
    }
  ],
  "total_rooms": 10,
  "raw_text": "Balcony  is entrance from living room .it is 15 feet length and 3 feet width aspect ratio as 5 over 1. Bathroom 1 is entrance from living room .it is 5 feet length and 3 feet width aspect ratio as 3 over 1. Bathroom 2 is entrance from living room .it is 5 feet length and 5 feet width aspect ratio as 3 over 3. Common room 1 is entrance from living room .it is 8 feet length and 12 feet width aspect ratio as 4 over 5. Common room2 is entrance from living room .it is 12 feet length and 12 feet width aspect ratio as 5 over 5. common room 2 is northeast corner room. kitchen is entrance from living room .it is 5 feet length and 10 feet width aspect ratio as 3 over 4.kitchen is northeast corner room. living room is entrance from west side.it  is 12 feet length and 25 feet width aspect ratio as 4 over 6.it is the big place compared to other rooms . Master room is entrance from living room .it is 10 feet length and 15 feet width aspect ratio as 4 over 5.it is southeast corner room.",
  "total_square_footage": 0,
  "id": "56217",
  "source_annotation": "data/raw/annotations/56217.txt",
  "source_image": "data/raw/images/56217.png"
}