{
  "rooms": [
    {
      "room": "bathroom",
      "position": null,
      "dimensions": {},
      "adjacent_rooms": [
        "common room",
        "master room"
      ],
      "directions": []
    },
    {
      "room": "common room",
      "position": "north",
      "dimensions": {},
      "adjacent_rooms": [],
      "directions": [
        "north",
        "east"
      ]
    },
    {
      "room": "kitchen",
      "position": null,
      "dimensions": {},
      "adjacent_rooms": [],
      "directions": []
    },
    {
      "room": "kitchen",
      "position": "center",
      "dimensions": {},
      "adjacent_rooms": [],
      "directions": [
        "center",
        "west"
      ]
    },
    {
      "room": "common room",
      "position": null,
      "dimensions": {},
      "adjacent_rooms": [
        "living room"
      ],
      "directions": []
    },
    {
      "room": "living room",
      "position": "south",
      "dimensions": {},
      "adjacent_rooms": [],
      "directions": [
        "south",
        "east"
      ]
    },
    {
      "room": "kitchen",
      "position": null,
      "dimensions": {},
      "adjacent_rooms": [],
      "directions": []
    },
    {
      "room": "master room",
      "position": "north",
      "dimensions": {},
      "adjacent_rooms": [
        "bathroom"
      ],
      "directions": [
        "north",
        "west"
      ]
    }
  ],
  "total_rooms": 8,
  "raw_text": "Bathroom is located between the common room and master room. It is at the center of north side. It has the rectangular size of 9 feet length and 5 feet width. common room is located at north east corner. It is adjacent to kitchen. It has the size of around 12 feet length and 10 feet width. kitchen is located at the center of west side. It is below the common room and adjacent to living room. It has the size of 12 feet length and 5 feet width. Living room is occupied south east area. It is in front of the kitchen and bath room. It has the area of  around 455 sqr. feet. master room is located at north west corner and adjacent to bathroom. It has the size of 20 feet length and 12 feet width.",
  "total_square_footage": 0,
  "id": "63239",
  "source_annotation": "data/raw/annotations/63239.txt",
  "source_image": "data/raw/images/63239.png"
}