{
  "rooms": [
    {
      "room": "balcony",
      "position": "northwest",
      "dimensions": {},
      "adjacent_rooms": [
        "kitchen"
      ],
      "directions": [
        "northwest"
      ]
    },
    {
      "room": "balcony",
      "position": "southwest",
      "dimensions": {},
      "adjacent_rooms": [
        "living room"
      ],
      "directions": [
        "southwest"
      ]
    },
    {
      "room": "bathroom",
      "position": "east",
      "dimensions": {},
      "adjacent_rooms": [
        "living room",
        "master room"
      ],
      "directions": [
        "east"
      ]
    },
    {
      "room": "common room",
      "position": "northeast",
      "dimensions": {},
      "adjacent_rooms": [
        "living room",
        "kitchen"
      ],
      "directions": [
        "northeast"
      ]
    },
    {
      "room": "kitchen",
      "position": "west",
      "dimensions": {},
      "adjacent_rooms": [
        "living room",
        "common room"
      ],
      "directions": [
        "west"
      ]
    },
    {
      "room": "living room",
      "position": "west",
      "dimensions": {},
      "adjacent_rooms": [],
      "directions": [
        "west"
      ]
    },
    {
      "room": "master room",
      "position": "southeast",
      "dimensions": {},
      "adjacent_rooms": [
        "living room",
        "bathroom"
      ],
      "directions": [
        "southeast"
      ]
    }
  ],
  "total_rooms": 7,
  "raw_text": "The balcony 1 is approximately 30 square feet, located in the northwest corner of the floor plan, and adjacent to the kitchen. The balcony 2 is approximately 60 square feet, located in the southwest corner of the floor plan, and adjacent to the living room. The bathroom is approximately 60 square feet, located in the east side of the floor plan, and adjacent to the living room and master room. The common room is approximately 100 square feet, located in the northeast corner of the floor plan, and adjacent to the living room and kitchen. The kitchen is approximately 70 square feet, located in the west side of the floor plan, and adjacent to the living room and common room. The living room is approximately 400 square feet, located in the west side of the floor plan, and adjacent to all rooms. The master room is approximately 150 square feet, located in the southeast corner of the floor plan, and adjacent to the living room and bathroom.",
  "total_square_footage": 0,
  "id": "6614",
  "source_annotation": "data/raw/annotations/6614.txt",
  "source_image": "data/raw/images/6614.png"
}